project4new/__init__.py
project4new-1.0.0.dist-info/METADATA
project4new-1.0.0.dist-info/WHEEL
project4new-1.0.0.dist-info/RECORD
