Metadata-Version: 2.1
Name: project4new
Version: 1.0.0
Summary: Assignment 4 info
License: MIT
Author: Tyson Johnson
Author-email: tjohns94@gmu.edu
Requires-Python: >=3.13,<4.0
Classifier: License :: OSI Approved :: MIT License
Classifier: Programming Language :: Python :: 3
Classifier: Programming Language :: Python :: 3.13
Requires-Dist: imageio (>=2.36.0,<3.0.0)
Requires-Dist: matplotlib (>=3.9.2,<4.0.0)
Requires-Dist: numpy (>=2.1.3,<3.0.0)
Requires-Dist: pandas (>=2.2.3,<3.0.0)
Requires-Dist: pathlib (>=1.0.1,<2.0.0)
Requires-Dist: tqdm (>=4.67.0,<5.0.0)
